[{"id":0,"gUrl":"https://play.famobi.com/kuli/A-DXC93"},
{"id":1,"gUrl":"https://play.famobi.com/wanderlust/A-DXC93"},
{"id":2,"gUrl":"https://play.famobi.com/taptastic-monsters/A-DXC93"},
{"id":3,"gUrl":"https://play.famobi.com/tiny-rifles/A-DXC93"},
{"id":4,"gUrl":"https://play.famobi.com/zombies-eat-my-stocking/A-DXC93"},
{"id":5,"gUrl":"https://play.famobi.com/rain-forest-hunter/A-DXC93"},
{"id":6,"gUrl":"https://play.famobi.com/mini-race-rush/A-DXC93"},
{"id":7,"gUrl":"https://play.famobi.com/angry-necromancer/A-DXC93"},
{"id":8,"gUrl":"https://play.famobi.com/burnin-rubber/A-DXC93"},
{"id":9,"gUrl":"https://play.famobi.com/sprint-club-nitro/A-DXC93"},
{"id":10,"gUrl":"https://play.famobi.com/turbotastic/A-DXC93"},
{"id":11,"gUrl":"https://play.famobi.com/speed-maniac/A-DXC93"},
{"id":12,"gUrl":"https://play.famobi.com/treasure-hunt/A-DXC93"},
{"id":13,"gUrl":"https://play.famobi.com/jewelish/A-DXC93"},
{"id":14,"gUrl":"https://play.famobi.com/clockwork-beetles/A-DXC93"},
{"id":15,"gUrl":"https://play.famobi.com/juicy-dash/A-DXC93"},
{"id":16,"gUrl":"https://play.famobi.com/jelly-collapse/A-DXC93"},
{"id":17,"gUrl":"https://play.famobi.com/back-to-candyland-1/A-DXC93"},
{"id":18,"gUrl":"https://play.famobi.com/fancy-diver/A-DXC93"},
{"id":19,"gUrl":"https://play.famobi.com/fruita-swipe-2/A-DXC93"},
{"id":20,"gUrl":"https://play.famobi.com/back-to-candyland-2/A-DXC93"},
{"id":21,"gUrl":"https://play.famobi.com/block-buster/A-DXC93"},
{"id":22,"gUrl":"https://play.famobi.com/back-to-candyland-3/A-DXC93"},
{"id":23,"gUrl":"https://play.famobi.com/back-to-candyland-4/A-DXC93"},
{"id":24,"gUrl":"https://play.famobi.com/fruit-swipe/A-DXC93"},
{"id":25,"gUrl":"https://play.famobi.com/pop-pop-rush/A-DXC93"},
{"id":26,"gUrl":"https://play.famobi.com/sweet-candies/A-DXC93"},
{"id":27,"gUrl":"https://play.famobi.com/stones-of-pharaoh/A-DXC93"}]